scHash/__init__.py
scHash/dataModule.py
scHash/scHashMain.py
scHash/util.py
scHash-1.4.4.3.dist-info/METADATA
scHash-1.4.4.3.dist-info/WHEEL
scHash-1.4.4.3.dist-info/top_level.txt
scHash-1.4.4.3.dist-info/RECORD
