Metadata-Version: 2.1
Name: scHash
Version: 1.4.4.3
Summary: scHash package for scRNA-seq data integration
Home-page: https://github.com/bowang-lab/scHash
Author: 
Author-email: 
License: MIT
Keywords: RNA-SEQ,Atlas,INTEGRATION
Classifier: Development Status :: 3 - Alpha
Classifier: License :: OSI Approved :: MIT License
Classifier: Programming Language :: Python :: 3
Classifier: Programming Language :: Python :: 3.4
Classifier: Programming Language :: Python :: 3.5
Classifier: Programming Language :: Python :: 3.6
Classifier: Programming Language :: Python :: 3.7
Requires-Dist: torch (>=1.0.0)
Requires-Dist: pytorch-lightning (>=1.6.5)
Requires-Dist: scipy (>=1.8.0)
Requires-Dist: numpy (>=1.22.1)
Requires-Dist: scikit-learn (>=1.0.2)
Requires-Dist: pandas (>=1.1.0)
Requires-Dist: anndata (>=0.8.0)
Requires-Dist: scanpy (>=1.7)
Requires-Dist: matplotlib (>=3.4.3)
